mmcfg/__init__.py
mmcfg/config.py
mmcfg/config_dict.py
mmcfg/lazy.py
mmcfg/utils.py
mmcfg-0.1.0.dist-info/LICENSE
mmcfg-0.1.0.dist-info/METADATA
mmcfg-0.1.0.dist-info/WHEEL
mmcfg-0.1.0.dist-info/RECORD
